rst2json/__init__.py
rst2json/__main__.py
rst2json/core.py
rst2json/knownopts.py
rst2json/transforms.py
rst2json/writers/__init__.py
rst2json/writers/_json_base.py
rst2json/writers/html4.py
rst2json/writers/html5.py
rst2json/writers/latex.py
rst2json/writers/xelatex.py
rst2json-0.5.1.dist-info/METADATA
rst2json-0.5.1.dist-info/WHEEL
rst2json-0.5.1.dist-info/entry_points.txt
rst2json-0.5.1.dist-info/licenses/LICENSE
rst2json-0.5.1.dist-info/RECORD
