Metadata-Version: 2.1
Name: rst2json
Version: 0.5.1
Summary: Split rendered reStructuredText into JSON
Project-URL: Source Code, https://github.com/jwodder/rst2json
Project-URL: Bug Tracker, https://github.com/jwodder/rst2json/issues
Author-email: John Thorvald Wodder II <rst2json@varonathe.org>
License-Expression: MIT
License-File: LICENSE
Keywords: JSON,docutils,reStructuredText,template,templating
Classifier: Environment :: Console
Classifier: Intended Audience :: Developers
Classifier: License :: OSI Approved :: MIT License
Classifier: Programming Language :: Python :: 3
Classifier: Programming Language :: Python :: 3 :: Only
Classifier: Programming Language :: Python :: 3.7
Classifier: Programming Language :: Python :: 3.8
Classifier: Programming Language :: Python :: 3.9
Classifier: Programming Language :: Python :: 3.10
Classifier: Programming Language :: Python :: 3.11
Classifier: Programming Language :: Python :: Implementation :: CPython
Classifier: Programming Language :: Python :: Implementation :: PyPy
Classifier: Topic :: Documentation
Classifier: Topic :: Software Development :: Documentation
Classifier: Topic :: Text Processing
Classifier: Topic :: Text Processing :: Markup :: HTML
Classifier: Topic :: Text Processing :: Markup :: LaTeX
Classifier: Topic :: Text Processing :: Markup :: reStructuredText
Requires-Python: >=3.7
Requires-Dist: docutils>=0.18.1
Requires-Dist: morecontext~=0.2
